bcubed/__init__.py
bcubed/extended.py
bcubed-1.5.dist-info/LICENSE
bcubed-1.5.dist-info/METADATA
bcubed-1.5.dist-info/WHEEL
bcubed-1.5.dist-info/top_level.txt
bcubed-1.5.dist-info/RECORD
