Metadata-Version: 2.1
Name: bcubed
Version: 1.5
Summary: Simple extended BCubed implementation in Python for clustering evaluation
Home-page: https://github.com/hhromic/python-bcubed
Author: Hugo Hromic
Author-email: hhromic@gmail.com
Maintainer: Hugo Hromic
Maintainer-email: hhromic@gmail.com
License: Apache-2.0
Download-URL: https://github.com/hhromic/python-bcubed/tarball/1.5
Keywords: bcubed,clustering,evaluation
Platform: all
Classifier: Environment :: Console
Classifier: Topic :: System :: Clustering
Classifier: Intended Audience :: Science/Research
Requires: numpy
Provides: bcubed
Requires-Dist: numpy
